illusion/__init__.py
illusion/__main__.py
illusion/api_client.py
illusion/cli.py
illusion/config.py
illusion/config_manager.py
illusion/context_store.py
illusion/git_manager.py
illusion/main.py
illusion/project_manager.py
illusion/ui.py
illusion_cli-1.0.1.dist-info/METADATA
illusion_cli-1.0.1.dist-info/WHEEL
illusion_cli-1.0.1.dist-info/entry_points.txt
illusion_cli-1.0.1.dist-info/top_level.txt
illusion_cli-1.0.1.dist-info/RECORD
