Metadata-Version: 2.4
Name: illusion-cli
Version: 1.0.1
Summary: AI-powered Python project and code generation assistant for multiple platform terminals.
Author: Phantom Illusions Studio - Ezra Mwanani | Mr. Blaq Beatle
License: MIT
Project-URL: Homepage, https://github.com/illusion-ai/illusion
Project-URL: Repository, https://github.com/illusion-ai/illusion
Project-URL: Issues, https://github.com/illusion-ai/illusion/issues
Requires-Python: >=3.9
Requires-Dist: rich>=13.0.0
Requires-Dist: openai>=1.0.0
Requires-Dist: requests>=2.0.0
